{
    "###_COMMENT_###" : "",
    "###_COMMENT_###" : "### 다운로드 받는 파일경로                   ###",
    "###_COMMENT_###" : "### 풀경로를 써주세요.                       ###",
    "DOWNLOADDIR": "/data/video/download",
    "###_COMMENT_###" : "### 이름이 변경된 파일이 저장될 경로         ###",
    "###_COMMENT_###" : "### 풀경로를 써주세요.                       ###",
    "TARGETDIR" : "/data/video/finish",
    "###_COMMENT_###" : "### 중복된 파일이 저장될 경로                ###",
    "###_COMMENT_###" : "### 풀경로를 써주세요.                       ###",
    "DUPEDIR" : "/data/video/dupe",
    "###_COMMENT_###" : "### 장르명으로 파일 자동 분류                ###",
    "###_COMMENT_###" : "### 변경될 파일이 저장될 경로 하단에 생성    ###",
    "###_COMMENT_###" : "### /장르명/제목/제목.E01.1801010.ETC.mp4    ###",
    "###_COMMENT_###" : "### Y,y 사용                                 ###",
    "###_COMMENT_###" : "### N,n 사용하지 않음                        ###",
    "IS_GENRE": "N",
    "###_COMMENT_###" : "### 폴더명에 연도 추가여부                   ###",
    "###_COMMENT_###" : "### Y,y 추가                                 ###",
    "###_COMMENT_###" : "### N,n 추가하지 않음                        ###",    
    "IS_YEAR": "Y",
    "###_COMMENT_###" : "### 파일명에 릴정보 추가여부                 ###",
    "###_COMMENT_###" : "### Y,y 추가                                 ###",
    "###_COMMENT_###" : "### N,n 추가하지 않음                        ###",
    "IS_ETC": "Y",
    "###_COMMENT_###" : "### 시즌으로 S01 추가여부                    ###",
    "###_COMMENT_###" : "### 에피소드번호가 1000이상은 자동으로 추가  ###",
    "###_COMMENT_###" : "### Y,y 추가                                 ###",
    "###_COMMENT_###" : "### N,n 추가하지 않음                        ###",    
    "IS_SEASON": "N",
    "###_COMMENT_###" : "### 에피소드번호 앞에 0추가 기본 값은 2      ###",
    "###_COMMENT_###" : "### 2일때 01,02, 03, 09, 10, 100             ###",
    "###_COMMENT_###" : "### 3일때 001, 002, 100, 1000                ###",    
    "ZEROFILL": "2",
    "###_COMMENT_###" : "### 파일명의 구분자 기본값은 .               ###",
    "###_COMMENT_###" : "### 제목.E01.190101.ETC.mp4                  ###",
    "DELIMITER": ".",
    "###_COMMENT_###" : ""
}
